LICENSE
MANIFEST.in
README.rst
VERSION
setup.cfg
setup.py
flask_boilerplate_utils/RedisSessionInterface.py
flask_boilerplate_utils/ReverseProxied.py
flask_boilerplate_utils/__init__.py
flask_boilerplate_utils/commands.py
flask_boilerplate_utils/filters.py
flask_boilerplate_utils/forms.py
flask_boilerplate_utils/jinja_globals.py
flask_boilerplate_utils/overrides.py
flask_boilerplate_utils.egg-info/PKG-INFO
flask_boilerplate_utils.egg-info/SOURCES.txt
flask_boilerplate_utils.egg-info/dependency_links.txt
flask_boilerplate_utils.egg-info/not-zip-safe
flask_boilerplate_utils.egg-info/requires.txt
flask_boilerplate_utils.egg-info/top_level.txt
flask_boilerplate_utils/templates/_boilerplate/macros.html