Metadata-Version: 1.0
Name: flask-boilerplate-utils
Version: 0.1.65
Summary: Additional functionality with easy upgrading for the flask-boilerplate.
Home-page: https://github.com/nickw444/flask-boilerplate-utils
Author: Nick Whyte
Author-email: nick@nickwhyte.com
License: UNKNOWN
Platform: UNKNOWN
